{
  "4khdhub": "https://4khdhub.dad",
  "bollyflix": "https://bollyflix.do",
  "gojo_base": "https://animetsu.bz",
  "hdmovie2": "https://hdmovie2.kiwi",
  "hdmoviesflix": "https://themovieflix.space",
  "hindmoviez": "https://hindmoviez.cafe",
  "moviesdrive": "https://moviesdrive.forum",
  "movies4u": "https://movies4u.fans",
  "moviesflix": "https://themovieflix.space",
  "multimovies": "https://multimovies.golf",
  "nfmirror": "https://net20.cc",
  "protonmovies": "https://m.protonmovies.space",
  "skymovies": "https://skymovieshd.mba",
  "uhdmovies": "https://uhdmovies.earth",
  "moviesmod": "https://moviesmod.build",
  "topmovies": "https://moviesleech.top",
  "vegamovies": "https://vegamovies.gt",
  "rogmovies": "https://rogmovies.world",
  "luxmovies": "https://luxmovies.cash",
  "gdflix": "https://new10.gdflix.net",
  "hubcloud": "https://hubcloud.foo",
  "katmoviehd": "https://katmoviehd.pictures",
  "moviesbaba": "https://moviesbaba.net",
  "hianime": "https://hianime.to",
  "toonstream": "https://toonstream.one",
  "dramadrip": "https://dramadrip.com",
  "xdmovies": "https://xdmovies.site",
  "nuvio": "https://nuviostreams.hayd.uk/providers=showbox,vidzee,vidsrc,vixsrc,mp4hydra"
}